jwt_user/Request.py
jwt_user/User.py
jwt_user/UserAuthorization.py
jwt_user/__init__.py
jwt_user/settings.py
jwt_user-0.0.9.dist-info/LICENSE.txt
jwt_user-0.0.9.dist-info/METADATA
jwt_user-0.0.9.dist-info/WHEEL
jwt_user-0.0.9.dist-info/top_level.txt
jwt_user-0.0.9.dist-info/RECORD
