Metadata-Version: 2.1
Name: jwt-user
Version: 0.0.9
Summary: Authorize user via jwt
Home-page: https://github.com/ilyashusterman/jwt_user
Author: Ilya shusterman
Author-email: shusterilyaman@gmail.com
License: UNKNOWN
Project-URL: Bug Reports, https://github.com/ilyashusterman/jwt_user/issues
Project-URL: Funding, https://donate.pypi.org
Project-URL: Source, https://github.com/ilyashusterman/jwt_user/
Keywords: sample setuptools development
Platform: UNKNOWN
Classifier: Development Status :: 5 - Production/Stable
Classifier: Intended Audience :: Developers
Classifier: Topic :: Software Development
Classifier: License :: OSI Approved :: MIT License
Classifier: Operating System :: OS Independent
Classifier: Programming Language :: Python :: 2
Classifier: Programming Language :: Python :: 2.7
Classifier: Programming Language :: Python :: 3
Classifier: Programming Language :: Python :: 3.4
Classifier: Programming Language :: Python :: 3.5
Classifier: Programming Language :: Python :: 3.6
Requires-Dist: PyJWT
Requires-Dist: bunch
Requires-Dist: six
